nmeasim/LICENSE
nmeasim/__init__.py
nmeasim/constants.py
nmeasim/gui.py
nmeasim/icon.ico
nmeasim/models.py
nmeasim/simulator.py
nmeasim-1.1.1.0.dist-info/METADATA
nmeasim-1.1.1.0.dist-info/WHEEL
nmeasim-1.1.1.0.dist-info/entry_points.txt
nmeasim-1.1.1.0.dist-info/top_level.txt
nmeasim-1.1.1.0.dist-info/RECORD
