Metadata-Version: 2.1
Name: nmeasim
Version: 1.1.1.0
Summary: A Python GNSS/NMEA receiver simulation
Author: Wei Li Jiang
Author-email: wjiang87@gmail.com
License: Copyright (c) 2021 Wei Li Jiang
Project-URL: homepage, https://gitlab.com/nmeasim/nmeasim
Project-URL: repository, https://gitlab.com/nmeasim/nmeasim
Keywords: gnss,glonass,gps,nmea,simulator
Classifier: Programming Language :: Python :: 3
Classifier: License :: OSI Approved :: MIT License
Requires-Python: >=3.7
Requires-Dist: pyserial
Requires-Dist: geographiclib
Requires-Dist: importlib.metadata; python_version < "3.8"
